uni_tool/__init__.py
uni_tool/core/__init__.py
uni_tool/core/errors.py
uni_tool/core/execution.py
uni_tool/core/expression_parser.py
uni_tool/core/expressions.py
uni_tool/core/models.py
uni_tool/core/universe.py
uni_tool/decorators/__init__.py
uni_tool/decorators/bind.py
uni_tool/decorators/tool.py
uni_tool/drivers/__init__.py
uni_tool/drivers/anthropic.py
uni_tool/drivers/base.py
uni_tool/drivers/deepseek.py
uni_tool/drivers/gemini.py
uni_tool/drivers/glm.py
uni_tool/drivers/markdown.py
uni_tool/drivers/openai.py
uni_tool/drivers/xml.py
uni_tool/filters/__init__.py
uni_tool/middlewares/__init__.py
uni_tool/middlewares/audit.py
uni_tool/middlewares/base.py
uni_tool/middlewares/logging.py
uni_tool/middlewares/monitor.py
uni_tool/utils/__init__.py
uni_tool/utils/docstring.py
uni_tool/utils/injection.py
uni_tool-0.4.0.dist-info/METADATA
uni_tool-0.4.0.dist-info/WHEEL
uni_tool-0.4.0.dist-info/licenses/LICENSE
uni_tool-0.4.0.dist-info/RECORD
