Metadata-Version: 2.4
Name: uni-tool
Version: 0.4.0
Summary: UniTools SDK - A unified tool registration and execution framework for LLM agents
License-File: LICENSE
Requires-Python: >=3.13
Requires-Dist: docstring-parser>=0.17.0
Requires-Dist: lark>=1.3.1
Requires-Dist: pre-commit>=4.5.1
Requires-Dist: pydantic>=2.10.0
Requires-Dist: ruff>=0.14.11
Provides-Extra: dev
Requires-Dist: pytest-asyncio>=0.24.0; extra == 'dev'
Requires-Dist: pytest>=8.0.0; extra == 'dev'
Requires-Dist: ruff>=0.14.0; extra == 'dev'
